CAETomo/__init__.py
CAETomo/alignment.py
CAETomo/cae.py
CAETomo/reconstruction.py
CAETomo-0.2.1.dist-info/METADATA
CAETomo-0.2.1.dist-info/WHEEL
CAETomo-0.2.1.dist-info/top_level.txt
CAETomo-0.2.1.dist-info/RECORD
